themetpy/__init__.py
themetpy/departments.py
themetpy/objects.py
themetpy/search.py
themetpy/utils.py
themetpy-1.0.2.dist-info/LICENSE
themetpy-1.0.2.dist-info/METADATA
themetpy-1.0.2.dist-info/WHEEL
themetpy-1.0.2.dist-info/RECORD
