Metadata-Version: 2.1
Name: themetpy
Version: 1.0.2
Summary: The Python Package for The MET Museum.
Home-page: https://github.com/Sabrina0222/TheMetPy
License: MIT
Author: Yuxi Sun
Requires-Python: >=3.9,<4.0
Classifier: License :: OSI Approved :: MIT License
Classifier: Programming Language :: Python :: 3
Classifier: Programming Language :: Python :: 3.9
Classifier: Programming Language :: Python :: 3.10
Classifier: Programming Language :: Python :: 3.11
Classifier: Programming Language :: Python :: 3.12
Classifier: Programming Language :: Python :: 3.13
Requires-Dist: requests (>=2.32.3,<3.0.0)
Project-URL: Documentation, https://themetpy.readthedocs.io/en/latest/
Project-URL: Repository, https://github.com/Sabrina0222/TheMetPy
